safenode-0.112.41.dist-info/METADATA
safenode-0.112.41.dist-info/WHEEL
safenode/__init__.py
safenode/core.py
safenode/_safenode.abi3.so
safenode-0.112.41.dist-info/RECORD
