Metadata-Version: 2.3
Name: safenode
Version: 0.112.41
Requires-Dist: maturin >=1.7.4
Requires-Dist: pip >=24.3.1
Summary: SAFE Network Node
Home-Page: https://maidsafe.net
Author: MaidSafe Developers <dev@maidsafe.net>
Author-email: MaidSafe Developers <dev@maidsafe.net>
License: GPL-3.0
Requires-Python: >=3.8
Project-URL: Source Code, https://github.com/maidsafe/safe_network
